{
  "configuration": {
    "collection": {
      "ignore_old_list": true,
      "is_completed": false,
      "item_capture_script": "../capture_item_toonkor.py -n 5",
      "list_url_list": [
        "https://tkr427.com/webtoon/8957"
      ],
      "sort_field_pattern": "\\t(\\d+)",
      "unit_size_per_day": 3
    },
    "extraction": {
      "render_js": true,
      "threshold_to_remove_html_with_incomplete_image": 5,
      "element_id_list": [
        "tnimg"
      ],
      "post_process_script_list": [
        "download_merge_split.py -c blackorwhite -m -b 100 -n 20"
      ],
      "force_sleep_between_articles": true
    },
    "rss": {
      "copyright": "Copyright (c) ToonKor. All rights reserved.",
      "description": "곤륜마협::ToonKor",
      "generator": "Terzeron's Feed Generator",
      "language": "ko",
      "link": "https://terzeron.com/devil_hero_in_kunlun.xml",
      "title": "곤륜마협::ToonKor",
      "url_prefix_for_guid": "https://toonkor132.com"
    }
  }
}