{
  "configuration": {
    "collection": {
      "render_js": false,
      "verify_ssl": true,
      "ignore_old_list": false,
      "is_completed": false,
      "item_capture_script": "../capture_item_naverwebtoon.py",
      "sort_field_pattern": null,
      "user_agent": null,
      "encoding": "utf-8",
      "referer": null,
      "timeout": null,
      "unit_size_per_day": null,
      "list_url_list": [
        "http://comic.naver.com/webtoon/list.nhn?titleId=754780"
      ],
      "post_process_script_list": []
    },
    "extraction": {
      "render_js": false,
      "verify_ssl": true,
      "bypass_element_extraction": false,
      "force_sleep_between_articles": false,
      "copy_images_from_canvas": false,
      "simulate_scrolling": false,
      "user_agent": null,
      "encoding": "utf8",
      "referer": null,
      "timeout": null,
      "element_id_list": [],
      "element_class_list": [
        "wt_viewer"
      ],
      "element_path_list": [],
      "post_process_script_list": [
        "download_image.py"
      ],
      "header_list": []
    },
    "rss": {
      "rss_title": "인간졸업::네이버",
      "rss_description": "인간졸업​::네이버 - 모바일 버전 RSS Feed",
      "rss_generator": "Terzeron's Feed Generator",
      "rss_copyright": "Copyright (c) NAVER Corp. All rights reserved.",
      "rss_link": "https://terzeron.com/graduation_from_humanity.xml",
      "rss_language": "ko",
      "rss_url_prefix_for_guid": null
    }
  }
}
