{
    "A Guide to Scala Collections: Exploring Monads in Scala Collections": "스칼라 컬렉션 가이드: 스칼라 컬렉션에서 모나드 살펴보기",
    "Modelling Reactive Systems with Event Storming and Domain-Driven Design": "이벤트 스토밍 및 도메인 중심 설계를 통한 반응형 시스템 모델링",
    "Transitioning to Scala": "Scala로 전환",
    "What is Reactive Programming?": "리액티브 프로그래밍이란 무엇인가요?",
    "A Journey into Reactive Streams": "리액티브 스트림으로의 여정",
    "Diving into Akka Streams": "아카 스트림 살펴보기",
    "Work Stealing: What Makes the Play Framework Fast": "작업 훔치기: 플레이 프레임워크를 빠르게 만드는 요소"
}